screenmonitormcp-2.0.1.dist-info/licenses/LICENSE
screenmonitormcp_v2/__init__.py
screenmonitormcp_v2/__main__.py
screenmonitormcp_v2/cli.py
screenmonitormcp_v2/mcp_main.py
screenmonitormcp_v2/core/__init__.py
screenmonitormcp_v2/core/ai_analyzer.py
screenmonitormcp_v2/core/ai_service.py
screenmonitormcp_v2/core/ai_vision.py
screenmonitormcp_v2/core/command_handler.py
screenmonitormcp_v2/core/config.py
screenmonitormcp_v2/core/connection.py
screenmonitormcp_v2/core/mcp_server.py
screenmonitormcp_v2/core/performance_monitor.py
screenmonitormcp_v2/core/screen_capture.py
screenmonitormcp_v2/core/streaming.py
screenmonitormcp_v2/models/__init__.py
screenmonitormcp_v2/models/requests.py
screenmonitormcp_v2/models/responses.py
screenmonitormcp_v2/server/__init__.py
screenmonitormcp_v2/server/app.py
screenmonitormcp_v2/server/config.py
screenmonitormcp_v2/server/main.py
screenmonitormcp_v2/server/routes.py
screenmonitormcp-2.0.1.dist-info/METADATA
screenmonitormcp-2.0.1.dist-info/WHEEL
screenmonitormcp-2.0.1.dist-info/entry_points.txt
screenmonitormcp-2.0.1.dist-info/top_level.txt
screenmonitormcp-2.0.1.dist-info/RECORD
