Metadata-Version: 2.4
Name: screenmonitormcp
Version: 2.0.1
Summary: Revolutionary AI Vision MCP Server - Streamable HTTP/SSE Architecture
Author-email: inkbytefo <inkbytefo@gmail.com>
Maintainer-email: inkbytefo <inkbytefo@gmail.com>
License-Expression: MIT
Project-URL: Homepage, https://github.com/inkbytefo/ScreenMonitorMCP
Project-URL: Repository, https://github.com/inkbytefo/ScreenMonitorMCP
Project-URL: Documentation, https://github.com/inkbytefo/ScreenMonitorMCP#readme
Project-URL: Bug Tracker, https://github.com/inkbytefo/ScreenMonitorMCP/issues
Project-URL: Changelog, https://github.com/inkbytefo/ScreenMonitorMCP/blob/main/CHANGELOG.md
Keywords: mcp,ai,screen-monitoring,computer-vision,automation,claude,openai,screen-capture,ui-automation,real-time,streaming,sse,websocket,http
Classifier: Development Status :: 4 - Beta
Classifier: Intended Audience :: Developers
Classifier: Operating System :: OS Independent
Classifier: Programming Language :: Python :: 3
Classifier: Programming Language :: Python :: 3.8
Classifier: Programming Language :: Python :: 3.9
Classifier: Programming Language :: Python :: 3.10
Classifier: Programming Language :: Python :: 3.11
Classifier: Programming Language :: Python :: 3.12
Classifier: Topic :: Software Development :: Libraries :: Python Modules
Classifier: Topic :: Multimedia :: Graphics :: Capture :: Screen Capture
Classifier: Topic :: Scientific/Engineering :: Artificial Intelligence
Classifier: Topic :: System :: Monitoring
Classifier: Topic :: Internet :: WWW/HTTP :: HTTP Servers
Classifier: Topic :: Internet :: WWW/HTTP :: Dynamic Content
Requires-Python: >=3.8
License-File: LICENSE
Requires-Dist: fastapi>=0.104.0
Requires-Dist: uvicorn[standard]>=0.24.0
Requires-Dist: python-multipart>=0.0.6
Requires-Dist: sse-starlette>=1.6.5
Requires-Dist: python-socketio>=5.9.0
Requires-Dist: websockets>=12.0
Requires-Dist: mss>=9.0.0
Requires-Dist: Pillow>=10.0.0
Requires-Dist: opencv-python>=4.8.0
Requires-Dist: numpy>=1.24.0
Requires-Dist: openai>=1.0.0
Requires-Dist: pytesseract>=0.3.10
Requires-Dist: easyocr>=1.7.0
Requires-Dist: pygetwindow>=0.0.9
Requires-Dist: pyautogui>=0.9.54
Requires-Dist: psutil>=5.9.0
Requires-Dist: python-dotenv>=1.0.0
Requires-Dist: pydantic>=2.0.0
Requires-Dist: pydantic-settings>=2.0.0
Requires-Dist: structlog>=23.0.0
Requires-Dist: prometheus-client>=0.17.0
Requires-Dist: tenacity>=8.2.0
Requires-Dist: pandas>=2.0.0
Requires-Dist: scikit-learn>=1.3.0
Requires-Dist: mcp[cli]>=1.12.0
Provides-Extra: dev
Requires-Dist: pytest>=7.0.0; extra == "dev"
Requires-Dist: pytest-asyncio>=0.21.0; extra == "dev"
Requires-Dist: httpx>=0.25.0; extra == "dev"
Requires-Dist: black>=23.0.0; extra == "dev"
Requires-Dist: isort>=5.12.0; extra == "dev"
Requires-Dist: flake8>=6.0.0; extra == "dev"
Requires-Dist: mypy>=1.5.0; extra == "dev"
Requires-Dist: pre-commit>=3.0.0; extra == "dev"
Provides-Extra: docs
Requires-Dist: sphinx>=7.0.0; extra == "docs"
Requires-Dist: sphinx-rtd-theme>=1.3.0; extra == "docs"
Requires-Dist: myst-parser>=2.0.0; extra == "docs"
Dynamic: license-file
